MANIFEST.in
README.md
gb-dl.py
setup.py
verify.py
gb_dl.egg-info/PKG-INFO
gb_dl.egg-info/SOURCES.txt
gb_dl.egg-info/dependency_links.txt
gb_dl.egg-info/not-zip-safe
gb_dl.egg-info/requires.txt
gb_dl.egg-info/top_level.txt