Metadata-Version: 2.1
Name: gb-dl
Version: 1.7.39
Summary: A python based utility to download courses from infosec4tc.teachable.com ,ehacking.net ,stackskills.com and designerup.co ...etc for personal offline use.
Home-page: https://github.com/barakagb/gb-dl
Author: barakagb
Author-email: barakagb@gmail.com
License: MIT
Keywords: infosec4tc stackskills -dl ehacking -dl teachable -dl coding with mosh academy-dl designerup gb-dl course downloader dl howto download teachle courses
Platform: UNKNOWN
Classifier: Programming Language :: Python :: 3.6
Classifier: Programming Language :: Python :: 3.8
Classifier: Programming Language :: Python :: 3.9
Requires-Python: >=3.6
